brimview_widgets/__init__.py
brimview_widgets/bls_data_visualizer.py
brimview_widgets/bls_do_treatment.py
brimview_widgets/bls_file_input.py
brimview_widgets/bls_metadata.py
brimview_widgets/bls_spectrum.py
brimview_widgets/bls_types.py
brimview_widgets/browser_file_selectors.py
brimview_widgets/debug_report_widget.py
brimview_widgets/environment.py
brimview_widgets/local_file_selectors.py
brimview_widgets/logging.py
brimview_widgets/models.py
brimview_widgets/progress_widget.py
brimview_widgets/s3file_selector.py
brimview_widgets/sampledata_loader.py
brimview_widgets/utils.py
brimview_widgets/widgets.py
brimview_widgets-0.3.3.dist-info/METADATA
brimview_widgets-0.3.3.dist-info/WHEEL
brimview_widgets-0.3.3.dist-info/licenses/LICENSE
brimview_widgets-0.3.3.dist-info/RECORD
